[
    {
        "title": "ANALISIS ANGGARAN SEBAGAI SALAH SATU ALAT PENGENDALIAN KINERJA PADA BADAN PENGELOLA KEUANGAN DAN ASET DAERAH (BPKAD) KOTA KENDARI",
        "year": 2025,
        "citations": 1
    },
    {
        "title": "Whistleblowing As an Effort to Reduce Fraud Actions",
        "year": 2021,
        "citations": 1
    },
    {
        "title": "Whistleblowing As an Effort to Reduce Fraud Actions",
        "year": 2022,
        "citations": 1
    },
    {
        "title": "Analisis varians anggaran pendapatan dan biaya (Studi pada PD. Pasar Kota Kendari)",
        "year": 2017,
        "citations": 1
    },
    {
        "title": "Analisis varians anggaran pendapatan dan biaya (Studi pada PD. Pasar Kota Kendari)",
        "year": 2020,
        "citations": 1
    },
    {
        "title": "Analisis varians anggaran pendapatan dan biaya (Studi pada PD. Pasar Kota Kendari)",
        "year": 2024,
        "citations": 1
    },
    {
        "title": "The Effect of Internal Control and Individual Morality on Fraud Prevention In Pt. Regional Development Bank of Southeast Sulawesi",
        "year": 2023,
        "citations": 1
    },
    {
        "title": "The Effect of Internal Control and Individual Morality on Fraud Prevention In Pt. Regional Development Bank of Southeast Sulawesi",
        "year": 2024,
        "citations": 2
    },
    {
        "title": "Sutrisno dan Rosidi, 2011",
        "year": 2013,
        "citations": 1
    },
    {
        "title": "Sutrisno dan Rosidi, 2011",
        "year": 2014,
        "citations": 1
    },
    {
        "title": "Sutrisno dan Rosidi, 2011",
        "year": 2016,
        "citations": 2
    },
    {
        "title": "Sutrisno dan Rosidi, 2011",
        "year": 2018,
        "citations": 1
    },
    {
        "title": "Sutrisno dan Rosidi, 2011",
        "year": 2021,
        "citations": 1
    },
    {
        "title": "Pengaruh Transparansi Dan Akuntabilitas Terhadap Kinerja Pengelolaan Anggaran Pada Uptd Taman Budaya Sulawesi Tenggara",
        "year": 2018,
        "citations": 1
    },
    {
        "title": "Pengaruh Transparansi Dan Akuntabilitas Terhadap Kinerja Pengelolaan Anggaran Pada Uptd Taman Budaya Sulawesi Tenggara",
        "year": 2019,
        "citations": 4
    },
    {
        "title": "Pengaruh Transparansi Dan Akuntabilitas Terhadap Kinerja Pengelolaan Anggaran Pada Uptd Taman Budaya Sulawesi Tenggara",
        "year": 2021,
        "citations": 3
    },
    {
        "title": "Pengaruh Transparansi Dan Akuntabilitas Terhadap Kinerja Pengelolaan Anggaran Pada Uptd Taman Budaya Sulawesi Tenggara",
        "year": 2023,
        "citations": 3
    },
    {
        "title": "Sutrisno & Rosidi. 2010. Analisis Faktor-faktor yang Berpengaruh Terhadap Keterandalan dan Ketepatwaktuan Pelaporan Keuangan Pada SKPD Pemerintah Daerah Kota Kendari",
        "year": 2016,
        "citations": 1
    },
    {
        "title": "Sutrisno & Rosidi. 2010. Analisis Faktor-faktor yang Berpengaruh Terhadap Keterandalan dan Ketepatwaktuan Pelaporan Keuangan Pada SKPD Pemerintah Daerah Kota Kendari",
        "year": 2017,
        "citations": 2
    },
    {
        "title": "Sutrisno & Rosidi. 2010. Analisis Faktor-faktor yang Berpengaruh Terhadap Keterandalan dan Ketepatwaktuan Pelaporan Keuangan Pada SKPD Pemerintah Daerah Kota Kendari",
        "year": 2018,
        "citations": 4
    },
    {
        "title": "Sutrisno & Rosidi. 2010. Analisis Faktor-faktor yang Berpengaruh Terhadap Keterandalan dan Ketepatwaktuan Pelaporan Keuangan Pada SKPD Pemerintah Daerah Kota Kendari",
        "year": 2019,
        "citations": 1
    },
    {
        "title": "Sutrisno & Rosidi. 2010. Analisis Faktor-faktor yang Berpengaruh Terhadap Keterandalan dan Ketepatwaktuan Pelaporan Keuangan Pada SKPD Pemerintah Daerah Kota Kendari",
        "year": 2020,
        "citations": 3
    },
    {
        "title": "Sutrisno & Rosidi. 2010. Analisis Faktor-faktor yang Berpengaruh Terhadap Keterandalan dan Ketepatwaktuan Pelaporan Keuangan Pada SKPD Pemerintah Daerah Kota Kendari",
        "year": 2021,
        "citations": 1
    },
    {
        "title": "Sutrisno & Rosidi. 2010. Analisis Faktor-faktor yang Berpengaruh Terhadap Keterandalan dan Ketepatwaktuan Pelaporan Keuangan Pada SKPD Pemerintah Daerah Kota Kendari",
        "year": 2022,
        "citations": 1
    },
    {
        "title": "Sutrisno & Rosidi. 2010. Analisis Faktor-faktor yang Berpengaruh Terhadap Keterandalan dan Ketepatwaktuan Pelaporan Keuangan Pada SKPD Pemerintah Daerah Kota Kendari",
        "year": 2024,
        "citations": 1
    },
    {
        "title": "Sutrisno & Rosidi. 2010. Analisis Faktor-faktor yang Berpengaruh Terhadap Keterandalan dan Ketepatwaktuan Pelaporan Keuangan Pada SKPD Pemerintah Daerah Kota Kendari",
        "year": 2025,
        "citations": 1
    },
    {
        "title": "Analisis Faktor–Faktor yang Berpengaruh terhadap Keterandalan dan Ketepatwaktuan Laporan Keuangan pada SKPD Pemerintah Daerah Kota Kendari",
        "year": 2012,
        "citations": 1
    },
    {
        "title": "Analisis Faktor–Faktor yang Berpengaruh terhadap Keterandalan dan Ketepatwaktuan Laporan Keuangan pada SKPD Pemerintah Daerah Kota Kendari",
        "year": 2014,
        "citations": 3
    },
    {
        "title": "Analisis Faktor–Faktor yang Berpengaruh terhadap Keterandalan dan Ketepatwaktuan Laporan Keuangan pada SKPD Pemerintah Daerah Kota Kendari",
        "year": 2015,
        "citations": 1
    },
    {
        "title": "Analisis Faktor–Faktor yang Berpengaruh terhadap Keterandalan dan Ketepatwaktuan Laporan Keuangan pada SKPD Pemerintah Daerah Kota Kendari",
        "year": 2016,
        "citations": 6
    },
    {
        "title": "Analisis Faktor–Faktor yang Berpengaruh terhadap Keterandalan dan Ketepatwaktuan Laporan Keuangan pada SKPD Pemerintah Daerah Kota Kendari",
        "year": 2017,
        "citations": 2
    },
    {
        "title": "Analisis Faktor–Faktor yang Berpengaruh terhadap Keterandalan dan Ketepatwaktuan Laporan Keuangan pada SKPD Pemerintah Daerah Kota Kendari",
        "year": 2018,
        "citations": 1
    },
    {
        "title": "Analisis Faktor–Faktor yang Berpengaruh terhadap Keterandalan dan Ketepatwaktuan Laporan Keuangan pada SKPD Pemerintah Daerah Kota Kendari",
        "year": 2020,
        "citations": 2
    },
    {
        "title": "Analisis Faktor–Faktor yang Berpengaruh terhadap Keterandalan dan Ketepatwaktuan Laporan Keuangan pada SKPD Pemerintah Daerah Kota Kendari",
        "year": 2021,
        "citations": 5
    },
    {
        "title": "Analisis Faktor–Faktor yang Berpengaruh terhadap Keterandalan dan Ketepatwaktuan Laporan Keuangan pada SKPD Pemerintah Daerah Kota Kendari",
        "year": 2022,
        "citations": 3
    },
    {
        "title": "Analisis Faktor–Faktor yang Berpengaruh terhadap Keterandalan dan Ketepatwaktuan Laporan Keuangan pada SKPD Pemerintah Daerah Kota Kendari",
        "year": 2024,
        "citations": 2
    },
    {
        "title": "Analisis Faktor–Faktor yang Berpengaruh terhadap Keterandalan dan Ketepatwaktuan Laporan Keuangan pada SKPD Pemerintah Daerah Kota Kendari",
        "year": 2025,
        "citations": 1
    }
]